puid/__init__.py
puid/__main__.py
puid/bits.py
puid/chars.py
puid/chars_error.py
puid/cli.py
puid/encoder.py
puid/entropy.py
puid/puid.py
puid/puid_error.py
puid/encoders/__init__.py
puid/encoders/alpha.py
puid/encoders/alphanum.py
puid/encoders/base16.py
puid/encoders/base32.py
puid/encoders/crockford32.py
puid/encoders/custom.py
puid/encoders/decimal.py
puid/encoders/hex.py
puid/encoders/safe32.py
puid/encoders/safe64.py
puid/encoders/safe_ascii.py
puid/encoders/symbol.py
puid/encoders/transformer.py
puid/encoders/word_safe32.py
puid_py-2.0.0.dist-info/licenses/AUTHORS.rst
puid_py-2.0.0.dist-info/licenses/LICENSE
puid_py-2.0.0.dist-info/METADATA
puid_py-2.0.0.dist-info/WHEEL
puid_py-2.0.0.dist-info/entry_points.txt
puid_py-2.0.0.dist-info/top_level.txt
puid_py-2.0.0.dist-info/RECORD
