Metadata-Version: 2.4
Name: puid-py
Version: 2.0.0
Summary: Simple, flexible and efficient generation of probably unique identifiers (`puid`, aka random strings) of intuitively specified entropy using pre-defined or custom characters, including unicode
Home-page: https://github.com/puid/python
Author: Paul Rogers
Author-email: paul@dingosky.com
License: MIT
Project-URL: Documentation, https://puid-py.readthedocs.io/
Project-URL: Changelog, https://puid-py.readthedocs.io/en/latest/changelog.html
Project-URL: Issue Tracker, https://github.com/puid/python/issues
Keywords: random string,random ID,uuid,secure token,security,token
Classifier: Development Status :: 5 - Production/Stable
Classifier: Intended Audience :: Developers
Classifier: License :: OSI Approved :: MIT License
Classifier: Operating System :: Unix
Classifier: Operating System :: POSIX
Classifier: Operating System :: Microsoft :: Windows
Classifier: Programming Language :: Python
Classifier: Programming Language :: Python :: 3
Classifier: Programming Language :: Python :: 3 :: Only
Classifier: Programming Language :: Python :: 3.7
Classifier: Programming Language :: Python :: 3.8
Classifier: Programming Language :: Python :: 3.9
Classifier: Programming Language :: Python :: 3.10
Classifier: Topic :: Utilities
Requires-Python: >=3.7
License-File: LICENSE
License-File: AUTHORS.rst
Dynamic: author
Dynamic: author-email
Dynamic: classifier
Dynamic: description
Dynamic: description-content-type
Dynamic: home-page
Dynamic: keywords
Dynamic: license
Dynamic: license-file
Dynamic: project-url
Dynamic: requires-python
Dynamic: summary
